{
  "schema_version": "1.0.0",
  "category": "npc",
  "id": "npc_039",
  "name": "Torque-N-R-39",
  "tags": [
    "paranoia_2e",
    "npc",
    "roster"
  ],
  "summary": "Research & Design operative with layered loyalties.",
  "source_text": {
    "book": "Paranoia 2E",
    "confidence": "derived"
  },
  "mechanics": {
    "service_group": "Research & Design",
    "secret_society": "Death Leopard",
    "mutation": "Machine Empathy",
    "trait": "pedantic",
    "clearance": "Yellow",
    "use_in_play": "briefing_authority"
  }
}
