{
  "schema_version": "1.0.0",
  "category": "book_page",
  "tags": [
    "shadowrun_6",
    "fulltext",
    "page_0005"
  ],
  "summary": "Shadowrun 6 Volltextseite 5.",
  "source_text": {
    "book": "Shadowrun_6_Downloadversion_2024.pdf",
    "page": 5
  },
  "mechanics": {
    "raw_text": "Fahren und Proben .............................199\nCrashs ................................................199\nFahrzeugmodi\ufb01  kationen .....................200\nFahrzeugkampf...................................200\nRiggen von Drohnen .................201\nInitiative von Drohnen ........................201\nAutosofts ...........................................201\nDas wilde Leben ................202\nNichtspieler charaktere ..............202\nSchergen ............................................203\nProfessionalit\u00e4tsstufe .........................203\nBeispiele f\u00fcr Schergen .......................203\nProfessionalit\u00e4tsstufe 0: \nSchl\u00e4gertypen und Mobs ...................204\nProfessionalit\u00e4tsstufe 1:                                      \nGangmitglieder und Ma\ufb01  aschl\u00e4ger .....205\nProfessionalit\u00e4tsstufe 2:  \nDie echten Gangs ...............................205\nProfessionalit\u00e4tsstufe 3: \nKonzernsicherheit ..............................206\nProfessionalit\u00e4tsstufe 4: \nSyndikatsgorillas ................................207\nProfessionalit\u00e4tsstufe 5: Polizei- \noder Konzern-Einsatzkommando .......207\nProfessionalit\u00e4tsstufe 6: HTR-Team ......208\nProfessionalit\u00e4tsstufe 7: \nElite-Konzernsicherheit ......................208\nProfessionalit\u00e4tsstufe 8: \nSpezialeinheiten .................................209\nProfessionalit\u00e4tsstufe 9: \nTop-Spezialeinheiten ..........................210\nProfessionalit\u00e4tsstufe 10: \nElite-Spezialeinheiten .........................210\nTop-Runner ........................................211\nConnections ..........................212\nBeispielconnections ...........................212\nCritter ..................................216\nMundane Critter .................................216\nErwachte Critter .................................216\nDracoformen ......................................219\nCritterkr\u00e4fte ...........................221\nAstrale Gestalt ....................................221\n\u00c4tzender Speichel ..............................222\nBewegung ..........................................222\nBewusstsein .......................................222\nBindung .............................................222\nDualwesen .........................................222\nEin\ufb02  uss ..............................................223\nElementarer Angriff ............................223\nEnergieaura ........................................223\nEssenzentzug .....................................223\nGedankensprache ...............................223\nGesteigerte Sinne ...............................224\nGift .....................................................224\nGifthauch ...........................................224\nGrauen ...............................................224\nImmunit\u00e4t ..........................................224\nInfektion .............................................224\nL\u00e4hmende Ber\u00fchrung ........................224\nL\u00e4hmendes Heulen ............................225\nMaterialisierung .................................225\nMimikry ..............................................225\nMystischer Panzer ..............................225\nNat\u00fcrliche Waffe .................................225\nNat\u00fcrlicher  Zauberspruch ..................225\nNebelgestalt .......................................225\nPanzer ................................................226\nPsychokinese .....................................226\nRegeneration ......................................226\nSchutz ................................................226\nSuche .................................................226\nTierbeherrschung ...............................226\nUnfall .................................................227\nVerschleierung ...................................227\nVerschlingen ......................................227\nVerst\u00e4rkter  Mystischer Panzer ...........227\nVerst\u00e4rkter Panzer ..............................227\nVersteinerung .....................................228\nVerwirrung .........................................228\nWetterbeherrschung ..........................228\nZwang ................................................228\nSchw\u00e4chen ............................228\nAllergie ...............................................228\nErzwungener Schlaf ...........................228\nEssenzverlust .....................................228\nGeschw\u00e4chte Sinne ............................228\nNahrungsbedarf .................................229\nUngebildet ..........................................229\nVerwundbarkeit ..................................229\nSpielleiterhinweise ........230\nWas macht eine \nSpielleiterin eigentlich? ......................230\nSpielvor bereitungen .................231\nKenne das Abenteuer .........................231\nKenne deine Runner ...........................232\nHalte ben\u00f6tigtes Material bereit ..........232\nSei dar\u00fcber im Bilde, was die \nSpieler erwarten und wollen ...............232\nPatzer und Kritische Patzer ........232\nReputation und Fahndungsstufe ...235\nReputation .........................................235\nFahndungsstufe .................................235\nConnections gewinnen ..............238\nSicherheit, Sensoren und Scanner ..238\nSicherheitszonen und ihre Stufen ......238\nVerschlossene T\u00fcren \nund andere Mechanismen ..................240\nBelohnungen f\u00fcr Runs ..............243\nKarma ................................................243\nGeld ...................................................243\nAusr\u00fcstung ............................244\nAusr\u00fcstungswerte ....................244\nVerf\u00fcgbarkeit .....................................244\nAktive Progammslots .........................245\nAngriffswerte .....................................245\nEssenzkosten .....................................245\nFahrzeugwerte ....................................245\nGer\u00e4testufe .........................................245\nHalterung ...........................................245\nKapazit\u00e4t ............................................245\nMatrixattribute ...................................245\nModus ................................................245\nMunition .............................................245\nSchadenswert ....................................245\nSprengwirkung ...................................246\nStufe ..................................................246\nVerteidigungswert ..............................246\nWiFi-Funktionalit\u00e4t .............................246\nAusr\u00fcstung kaufen und verkaufen ..246\nStandardwaren ...................................246\nAnfangsausr\u00fcstung ............................246\nAusr\u00fcstung verkaufen ........................246\nAusr\u00fcstung verbergen ........................246\nKostenanpassung f\u00fcr Gr\u00f6sse .............247\nNahkampfwaffen .....................247\nKlingenwaffen ....................................247\nKn\u00fcppel ..............................................248\nAndere Nahkampfwaffen ....................249\nProjektil-  und Wurfwaffen ..........250\nFeuerwaffen ..........................251\nTaser ..................................................251\nHoldout-Pistolen ................................251\nLeichte Pistolen ..................................252\nAutomatikpistolen ..............................253\nSchwere Pistolen ...............................253\nMaschinenpistolen .............................254\nSchrot\ufb02  inten ......................................255\nJagdgewehre ......................................256\nSturmgewehre ...................................256\nScharfsch\u00fctzengewehre .....................257\nMaschinengewehre ............................257\nExotische Waffen ....................258\nSpezielle Waffen .................................258\nGranat- und  Raketenwerfer ................258\nWaffenzubeh\u00f6r .......................259\nMunition ...............................261\nAlles, was BUMM macht............262\nGranaten ............................................262\nRaketen und Lenkraketen ...................263\nSprengstoffe ......................................264\nKleidung  und Panzerung ............265\nKleidung .............................................265\nPanzerung ..........................................265\nPanzerungs modi\ufb01  kationen .................266\nHelme .................................................267\nSchilde ...............................................267\nElektronik .............................268\nKommlinks .........................................268\nCyberdecks ........................................268\nRiggerkonsolen ..................................268\nElektronikzubeh\u00f6r ..............................269\nRFID-Chips .........................................270\nKommunikation und \n Gegenma\u00dfnahmen .............................270\nSoftware ...............................271\nID und Credsticks ....................273\nWerkzeuge ............................274\nOptische  Ger\u00e4te & \nSichtverst\u00e4rkungen ..................274\nOptische Ger\u00e4te ..................................274\nSichtverst\u00e4rkungen ............................275\nAudioger\u00e4te & -verst\u00e4rkungen .....276\nAudioger\u00e4te ........................................276\nAudioverst\u00e4rkungen ...........................277\nSensoren ..............................277\nSensorfunktionen ...............................278\nFahren und Proben\n .............................\n199\nCrashs\n ................................................\n199\nFahrzeugmodi\ufb01  kationen\n .....................\n200\nFahrzeugkampf\n...................................\n200\nRiggen von Drohnen\n .................\n201\nInitiative von Drohnen\n ........................\n201\nAutosofts\n ...........................................\n201\nDas wilde Leben\n ................\n202\nNichtspieler charaktere\n ..............\n202\nSchergen\n ............................................\n203\nProfessionalit\u00e4tsstufe\n .........................\n203\nBeispiele f\u00fcr Schergen\n .......................\n203\nProfessionalit\u00e4tsstufe 0: \nSchl\u00e4gertypen und Mobs\n ...................\n204\nProfessionalit\u00e4tsstufe 1:                                      \nGangmitglieder und Ma\ufb01  aschl\u00e4ger\n .....\n205\nProfessionalit\u00e4tsstufe 2:  \nDie echten Gangs\n ...............................\n205\nProfessionalit\u00e4tsstufe 3: \nKonzernsicherheit\n ..............................\n206\nProfessionalit\u00e4tsstufe 4: \nSyndikatsgorillas\n ................................\n207\nProfessionalit\u00e4tsstufe 5: Polizei- \noder Konzern-Einsatzkommando\n .......\n207\nProfessionalit\u00e4tsstufe 6: HTR-Team\n ......\n208\nProfessionalit\u00e4tsstufe 7: \nElite-Konzernsicherheit\n ......................\n208\nProfessionalit\u00e4tsstufe 8: \nSpezialeinheiten\n .................................\n209\nProfessionalit\u00e4tsstufe 9: \nTop-Spezialeinheiten\n ..........................\n210\nProfessionalit\u00e4tsstufe 10: \nElite-Spezialeinheiten\n .........................\n210\nTop-Runner\n ........................................\n211\nConnections\n ..........................\n212\nBeispielconnections\n ...........................\n212\nCritter\n ..................................\n216\nMundane Critter\n .................................\n216\nErwachte Critter\n .................................\n216\nDracoformen\n ......................................\n219\nCritterkr\u00e4fte\n ...........................\n221\nAstrale Gestalt\n ....................................\n221\n\u00c4tzender Speichel\n ..............................\n222\nBewegung\n ..........................................\n222\nBewusstsein\n .......................................\n222\nBindung\n .............................................\n222\nDualwesen\n .........................................\n222\nEin\ufb02  uss\n ..............................................\n223\nElementarer Angriff\n ............................\n223\nEnergieaura\n ........................................\n223\nEssenzentzug\n .....................................\n223\nGedankensprache\n ...............................\n223\nGesteigerte Sinne\n ...............................\n224\nGift\n .....................................................\n224\nGifthauch\n ...........................................\n224\nGrauen\n ...............................................\n224\nImmunit\u00e4t\n ..........................................\n224\nInfektion\n .............................................\n224\nL\u00e4hmende Ber\u00fchrung\n ........................\n224\nL\u00e4hmendes Heulen\n ............................\n225\nMaterialisierung\n 225\nMystischer Panzer\n ..............................\n225\nNat\u00fcrliche Waffe\n .................................\n225\nNat\u00fcrlicher  Zauberspruch\n ..................\n225\nNebelgestalt\n .......................................\n225\nPanzer\n ................................................\n226\nPsychokinese\n .....................................\n226\nRegeneration\n ......................................\n226\nSchutz\n ................................................\n226\nSuche\n .................................................\n226\nTierbeherrschung\n ...............................\n226\nUnfall\n .................................................\n227\nVerschleierung\n ...................................\n227\nVerschlingen\n ......................................\n227\nVerst\u00e4rkter  Mystischer Panzer\n ...........\n227\nVerst\u00e4rkter Panzer\n ..............................\n227\nVersteinerung\n .....................................\n228\nVerwirrung\n .........................................\n228\nWetterbeherrschung\n ..........................\n228\nZwang\n ................................................\n228\nSchw\u00e4chen\n ............................\n228\nAllergie\n ...............................................\n228\nErzwungener Schlaf\n ...........................\n228\nEssenzverlust\n .....................................\n228\nGeschw\u00e4chte Sinne\n ............................\n228\nNahrungsbedarf\n .................................\n229\nUngebildet\n ..........................................\n229\nVerwundbarkeit\n ..................................\n229\nSpielleiterhinweise\n ........\n230\nWas macht eine \nSpielleiterin eigentlich?\n ......................\n230\nSpielvor bereitungen\n .................\n231\nKenne das Abenteuer\n .........................\n231\nKenne deine Runner\n ...........................\n232\nHalte ben\u00f6tigtes Material bereit\n ..........\n232\nSei dar\u00fcber im Bilde, was die \nSpieler erwarten und wollen\n ...............\n232\nPatzer und Kritische Patzer\n ........\n232\nReputation und Fahndungsstufe\n ...\n 235\nReputation\n .........................................\n235\nFahndungsstufe\n .................................\n235\nConnections gewinnen\n ..............\n238\nSicherheit, Sensoren und Scanner\n ..\n238\nSicherheitszonen und ihre Stufen\n ......\n238\nVerschlossene T\u00fcren \nund andere Mechanismen\n ..................\n240\nBelohnungen f\u00fcr Runs\n ..............\n243\nKarma\n ................................................\n243\nGeld\n ...................................................\n243\nAusr\u00fcstung\n ............................\n244\nAusr\u00fcstungswerte\n ....................\n244\nVerf\u00fcgbarkeit\n .....................................\n244\nAktive Progammslots\n .........................\n245\nAngriffswerte\n .....................................\n245\nEssenzkosten\n .....................................\n245\nFahrzeugwerte\n ....................................\n245\nGer\u00e4testufe\n .........................................\n245\nHalterung\n ...........................................\n245\nKapazit\u00e4t\n ............................................\n245\nMatrixattribute\n ...................................\n245\nModus\n 245\nSchadenswert\n ....................................\n245\nSprengwirkung\n ...................................\n246\nStufe\n ..................................................\n246\nVerteidigungswert\n ..............................\n246\nWiFi-Funktionalit\u00e4t\n .............................\n246\nAusr\u00fcstung kaufen und verkaufen\n ..\n246\nStandardwaren\n ...................................\n246\nAnfangsausr\u00fcstung\n ............................\n246\nAusr\u00fcstung verkaufen\n ........................\n246\nAusr\u00fcstung verbergen\n ........................\n246\nKostenanpassung f\u00fcr Gr\u00f6sse\n .............\n247\nNahkampfwaffen\n .....................\n247\nKlingenwaffen\n ....................................\n247\nKn\u00fcppel\n ..............................................\n248\nAndere Nahkampfwaffen\n ....................\n249\nProjektil-  und Wurfwaffen\n ..........\n250\nFeuerwaffen\n ..........................\n251\nTaser\n ..................................................\n251\nHoldout-Pistolen\n ................................\n251\nLeichte Pistolen\n ..................................\n252\nAutomatikpistolen\n ..............................\n253\nSchwere Pistolen\n ...............................\n253\nMaschinenpistolen\n .............................\n254\nSchrot\ufb02  inten\n ......................................\n255\nJagdgewehre\n ......................................\n256\nSturmgewehre\n ...................................\n256\nScharfsch\u00fctzengewehre\n .....................\n257\nMaschinengewehre\n ............................\n257\nExotische Waffen\n ....................\n258\nSpezielle Waffen\n .................................\n258\nGranat- und  Raketenwerfer\n ................\n258\nWaffenzubeh\u00f6r\n .......................\n259\nMunition\n ...............................\n261\nAlles, was BUMM macht\n............\n262\nGranaten\n ............................................\n262\nRaketen und Lenkraketen\n ...................\n263\nSprengstoffe\n ......................................\n264\nKleidung  und Panzerung\n ............\n265\nKleidung\n .............................................\n265\nPanzerung\n ..........................................\n265\nPanzerungs modi\ufb01  kationen\n .................\n266\nHelme\n .................................................\n267\nSchilde\n ...............................................\n267\nElektronik\n .............................\nElektronik\n .............................\nElektronik\n 268\nKommlinks\n .........................................\n268\nCyberdecks\n ........................................\n268\nRiggerkonsolen\n ..................................\n268\nElektronikzubeh\u00f6r\n ..............................\n269\nRFID-Chips\n .........................................\n270\nKommunikation und \n Gegenma\u00dfnahmen\n .............................\n270\nSoftware\n ...............................\n271\nID und Credsticks\n ....................\n273\nWerkzeuge\n ............................\n274\nOptische  Ger\u00e4te & \nSichtverst\u00e4rkungen\n ..................\n274\nOptische Ger\u00e4te\n ..................................\n274\nSichtverst\u00e4rkungen\n ............................\n275\nAudioger\u00e4te & -verst\u00e4rkungen\n .....\n276\nAudioger\u00e4te\n ........................................\n276\nAudioverst\u00e4rkungen\n ...........................\n277\nSensoren\n 277\nSHADOWRUN: SECHSTE EDITION\n4  //  INHAL T "
  }
}
