{
  "schema_version": "1.0.0",
  "category": "rules_fulltext_chunk",
  "tags": [
    "add_2e",
    "book_conversion",
    "phase_2",
    "tsr_inc_ad_and_d_2nd_edition_dragonlance_heroes_of_steel",
    "conditions"
  ],
  "summary": "Phase-2 Regelchunk: conditions aus TSR Inc - AD&D 2nd Edition - Dragonlance_ Heroes of Steel.pdf.",
  "source_text": {
    "book": "TSR Inc - AD&D 2nd Edition - Dragonlance_ Heroes of Steel",
    "source_file": "TSR Inc - AD&D 2nd Edition - Dragonlance_ Heroes of Steel.pdf",
    "text": "[PDF_PAGE 153 | score=5] Creating Knightly Circles In the Fifth Age, the two thousand year-old Solamnic Knighthood has spread throughout western Ansalon. The most important of its circles are described in the Appendix to the Night and Day sourcebook. But players an Narrators can invent their own Solamnic circles—and Legion of Steel circles and cells—anywhere in the continent, using the tips and charts here. In the course of an adventure, a Knight of Solamnia hero may wish to draw funds or obtain equipment from his Order. The charts below can determine the level of resources available from the Knighthood in the area (or from the Legion). They also show the reputation of the circle's (or cell's) commander, for use whe\n[PDF_PAGE 71 | score=3] Impossible (24) Some combat actions carry the potential for a permanent effect or seem impossible. Succeeding would be a once- in-a-lifetime occurrence for most mor- tals. Examples include the following: Shooting a grape off the top of some- one’s head while blindfolded Snatching an arrow right out of the air Maiming an opponent with one blow Combat Advantages Of course, not all fights are even. Some- times one side will have the advantage of surprise, terrain, or size over a foe. Chap- ter Four in the Book of the Fifth Age describes conditions regarding surprise and related disadvantages. This section describes advantages (or disadvantages) for other common conditions. Condition Off./Def. M\n[PDF_PAGE 146 | score=2] Scene Four: The Camp The heroes have come to this scene either as captives of the brutes or by tracking the prison wagon’s trail here. Narrators may have to alter some description, depending on whether the heroes are freely reconnoi- tering the camp or imprisoned here. Overview The brutes take their captives to a ruined village. When they have collected enough prisoners, Khellendros himself flies in and conducts the spawning ritual. Getting Started The narrator can refer back to the sidebar in the previous scene for details on spawn. First Impressions If the heroes have been captured, they see the scene described below from the van- tage point of a prison wagon pulling into camp. The brutes \n[PDF_PAGE 23 | score=1] The Rider Ansalon’s more arid plains are home to several tribes of horse barbarians. These mounted wanderers resemble the plains barbarian warriors described earlier in this section, but their way of life revolves mostly around their horses. The largest group of riders lives in northeastern Ansalon and recognizes the overlordship of King Shredler Kerian of Nordmaar in North Keep. One such rider is Voram Cidroveh, mentioned in the “Mohrlex” entry in Chapter Two of Dusk or Dawn. Role-Playing A rider’s most valued possession is his horse, which he cares for as through it were a member of the family. Not other- wise tied to land or property, the rider remains content with the few meager possessi\n[PDF_PAGE 30 | score=1] KNIGHTLY ORDERS KNIGHTLY ORDERS 27 The number of circles throughout Ansalon has fluctuated greatly over the years. However, new ones are formed each year as the Solamnic Knights solidify their position against the Great Dragons. Appendix Two lists the best-known circles operating during the Fifth Age. Knightly Offices Offices within the Knighthood generally are assigned by popular vote. Office hold- ers are well respected, but have no special rights or precedence except in matters directly related to their office. The leader of a circle, for example, is the master at his own council table, but defers to more experienced Knights on other matters. The High Knights and the Grand Master are exce\n[PDF_PAGE 43 | score=1] which also can extend to govern the lives of each member of the Knighthood. He required strict adherence to the Code, but always considered each case on its own merits and was known to make excep- tions based on circumstances. After the War of the Lance-during Ariakan’s time as a prisoner, and later a student, in the High Clerist’s Tower—the Knights of Solamnia under Lord Gunthar held knightly councils to consider revi- sions to their Measure. After observing many of these council meetings, Ariakan decided they were a waste of time. Indeed, before Lord Gunthar’s reforms, the Solamnic Knights were prone to endless bickering over trivial points of law and honor. Ariakan established his Code to\n[PDF_PAGE 54 | score=1] treated as experienced heroes seeking to join the Order (see next page). Those with a Novice reputation or lower who pass the interview are turned over to a mentor for training, as described below. Joining Anonymously Applicants who wish to join the Legion anonymously should come to Solace and stay the night at the Inn of the Last Home. A brief word with the staff alerts the Legion to the candidate’s presence. If an applicant comes recommended by a high-ranking Legionnaire sponsor, the sponsor will have given him a star-shaped jewel—reminiscent of the Legion’s star- jewel symbol—to pass to the Inn staff. In any case, the anonymous applicant can expect to be interviewed within two days. Those\n[PDF_PAGE 64 | score=1] All the action descriptions included here assume a fairly even fight, with nei- ther side having any significant advantage over the other. When this isn’t the case, Narrators should refer to “Combat Advantages” on page 68. Some of the actions below have no indicated difficulty, action ability, or opposition ability, because they apply to the action the hero just attempted-the player does not play another card. While reading these sample actions, players should think of creative ways to combine or alter them to form new actions. Some examples are provided. Offensive Actions When attacking a foe, the hero has a number of advanced combat options. Some examples of creative attacks follow, arrang"
  },
  "mechanics": {
    "topic": "conditions",
    "keywords": [
      "add_2e",
      "condition",
      "conditions",
      "held",
      "tsr_inc_ad_and_d_2nd_edition_dragonlance_heroes_of_steel"
    ],
    "injection_priority": "core",
    "confidence": 0.45,
    "page_refs": [
      23,
      30,
      43,
      54,
      64,
      71,
      146,
      153
    ],
    "raw_text": "[PDF_PAGE 153 | score=5] Creating Knightly Circles In the Fifth Age, the two thousand year-old Solamnic Knighthood has spread throughout western Ansalon. The most important of its circles are described in the Appendix to the Night and Day sourcebook. But players an Narrators can invent their own Solamnic circles—and Legion of Steel circles and cells—anywhere in the continent, using the tips and charts here. In the course of an adventure, a Knight of Solamnia hero may wish to draw funds or obtain equipment from his Order. The charts below can determine the level of resources available from the Knighthood in the area (or from the Legion). They also show the reputation of the circle's (or cell's) commander, for use whe\n[PDF_PAGE 71 | score=3] Impossible (24) Some combat actions carry the potential for a permanent effect or seem impossible. Succeeding would be a once- in-a-lifetime occurrence for most mor- tals. Examples include the following: Shooting a grape off the top of some- one’s head while blindfolded Snatching an arrow right out of the air Maiming an opponent with one blow Combat Advantages Of course, not all fights are even. Some- times one side will have the advantage of surprise, terrain, or size over a foe. Chap- ter Four in the Book of the Fifth Age describes conditions regarding surprise and related disadvantages. This section describes advantages (or disadvantages) for other common conditions. Condition Off./Def. M\n[PDF_PAGE 146 | score=2] Scene Four: The Camp The heroes have come to this scene either as captives of the brutes or by tracking the prison wagon’s trail here. Narrators may have to alter some description, depending on whether the heroes are freely reconnoi- tering the camp or imprisoned here. Overview The brutes take their captives to a ruined village. When they have collected enough prisoners, Khellendros himself flies in and conducts the spawning ritual. Getting Started The narrator can refer back to the sidebar in the previous scene for details on spawn. First Impressions If the heroes have been captured, they see the scene described below from the van- tage point of a prison wagon pulling into camp. The brutes \n[PDF_PAGE 23 | score=1] The Rider Ansalon’s more arid plains are home to several tribes of horse barbarians. These mounted wanderers resemble the plains barbarian warriors described earlier in this section, but their way of life revolves mostly around their horses. The largest group of riders lives in northeastern Ansalon and recognizes the overlordship of King Shredler Kerian of Nordmaar in North Keep. One such rider is Voram Cidroveh, mentioned in the “Mohrlex” entry in Chapter Two of Dusk or Dawn. Role-Playing A rider’s most valued possession is his horse, which he cares for as through it were a member of the family. Not other- wise tied to land or property, the rider remains content with the few meager possessi\n[PDF_PAGE 30 | score=1] KNIGHTLY ORDERS KNIGHTLY ORDERS 27 The number of circles throughout Ansalon has fluctuated greatly over the years. However, new ones are formed each year as the Solamnic Knights solidify their position against the Great Dragons. Appendix Two lists the best-known circles operating during the Fifth Age. Knightly Offices Offices within the Knighthood generally are assigned by popular vote. Office hold- ers are well respected, but have no special rights or precedence except in matters directly related to their office. The leader of a circle, for example, is the master at his own council table, but defers to more experienced Knights on other matters. The High Knights and the Grand Master are exce\n[PDF_PAGE 43 | score=1] which also can extend to govern the lives of each member of the Knighthood. He required strict adherence to the Code, but always considered each case on its own merits and was known to make excep- tions based on circumstances. After the War of the Lance-during Ariakan’s time as a prisoner, and later a student, in the High Clerist’s Tower—the Knights of Solamnia under Lord Gunthar held knightly councils to consider revi- sions to their Measure. After observing many of these council meetings, Ariakan decided they were a waste of time. Indeed, before Lord Gunthar’s reforms, the Solamnic Knights were prone to endless bickering over trivial points of law and honor. Ariakan established his Code to\n[PDF_PAGE 54 | score=1] treated as experienced heroes seeking to join the Order (see next page). Those with a Novice reputation or lower who pass the interview are turned over to a mentor for training, as described below. Joining Anonymously Applicants who wish to join the Legion anonymously should come to Solace and stay the night at the Inn of the Last Home. A brief word with the staff alerts the Legion to the candidate’s presence. If an applicant comes recommended by a high-ranking Legionnaire sponsor, the sponsor will have given him a star-shaped jewel—reminiscent of the Legion’s star- jewel symbol—to pass to the Inn staff. In any case, the anonymous applicant can expect to be interviewed within two days. Those\n[PDF_PAGE 64 | score=1] All the action descriptions included here assume a fairly even fight, with nei- ther side having any significant advantage over the other. When this isn’t the case, Narrators should refer to “Combat Advantages” on page 68. Some of the actions below have no indicated difficulty, action ability, or opposition ability, because they apply to the action the hero just attempted-the player does not play another card. While reading these sample actions, players should think of creative ways to combine or alter them to form new actions. Some examples are provided. Offensive Actions When attacking a foe, the hero has a number of advanced combat options. Some examples of creative attacks follow, arrang"
  }
}
