{
  "schema_version": "1.0.0",
  "category": "rules_fulltext_chunk",
  "tags": [
    "add_2e",
    "book_conversion",
    "phase_2",
    "tsr_inc_ad_and_d_2nd_edition_dragonlance_heroes_of_sorcery_text",
    "attribute_bonuses"
  ],
  "summary": "Phase-2 Regelchunk: attribute_bonuses aus TSR Inc - AD&D 2nd Edition - Dragonlance_ Heroes of Sorcery_text.pdf.",
  "source_text": {
    "book": "TSR Inc - AD&D 2nd Edition - Dragonlance_ Heroes of Sorcery_text",
    "source_file": "TSR Inc - AD&D 2nd Edition - Dragonlance_ Heroes of Sorcery_text.pdf",
    "text": "[PDF_PAGE 64 | score=12] Innovative Spells Spouting sorcerous theory and postu- lating about the required energy and potential effects of a new spell are one thing; actually casting it and achieving the desired results is quite another. No matter how well a sorcerer understands his art, things never translate exactly as expected when taking a spell from the- ory to practice. For this reason, the first success with a spell is more difficult to achieve than any other. Once a hero has actually produced the effect, repeating it is significantly easier. One thing that makes attempting new spells easier is abundant prepara- tion. A hero who reads a sorcerer's notes (or better yet, talks to him per- sonally) about similar \n[PDF_PAGE 63 | score=7] 2 Q DN ds z с: 254 Sis AS A ~ ¢ ay > S^ ^. NN Mi IX 1 ASA ) „кл CNN $ never increase and, іп most situations, the total difficulty will equal the base difficulty. However, the Narrator may assess a penalty to the base difficulty whenever he deems that the circum- stances surrounding the sorcerer make it hard for him to concentrate properly or might otherwise interfere with his spellcasting. Penalties should be assessed based on how disruptive the distraction is. A raucous noise or sudden jostle might be cause for a 1-point penalty, while casting a spell in the midst of a great battle may result in a 5-point penalty. Trying to keep enough concentration to cast while under the close scrutiny o\n[PDF_PAGE 30 | score=5] | must have Endurance scores of no the Order is particular about exactly how and by whom it is represented. The Knights expect nothing short of perfection from themselves, and they are equally demanding of their auxil- iary members. Requirements While the Knights themselves admit only civilized human and half-elf warriors into their ranks, the auxiliary is open to anyone who meets the rigid chivalric standards for entrance. Sorcerer heroes are more likely to encounter aloofness among the Knights because of their profession than from any kind of racism, for the Knights are not entirely comfortable with sorcery yet. Auxiliary members need not meet all the physical requirements demanded of Knig\n[PDF_PAGE 16 | score=3] battle, the Advantages While some might say that sorcerous skill alone is a huge advantage in a re one or two other points at which battle mages excel. Because sorcerers generally have had more education than the average sol- dier, they have had more exposure to Krynn's history, including military his- tory. This gives battle mages, who have also specialized in military exercises, a solid grip on military theory. While this does not help much in the middle of a skirmish, it does give these heroes an edge when making battle plans (though it does not necessarily make them qualified generals). When orga- nizing an attack or defense involving twenty-five or more people, a battle mage gains a +3 \n[PDF_PAGE 25 | score=3] ISON = — N ~ «S E \"di <А Advantages Once again, because being a Thorn Knight is a subsequent step from being a Knight of the Lily, these heroes maintain the martial advan- tages all Knights of Takhisis have. Any card played to close with the enemy during battle is automatically trump. Any card played for melee attack while the Knight is riding a mount is automatically trump. The hatred the Dark Knights feel for members of the Legion of Steel, how- ever, manifests itself differently in Thorn Knights. They do not get bonuses for melee combat as do Lily Knights. Instead, any cards played for sorcerous actions against Legionnaires are automatically trump. Furthermore, because of the emphasis the\n[PDF_PAGE 33 | score=3] мч Qib t VEN е, = SSS EE С у Y: the card used for the hero’s nature will come into play regularly (see “Disad- vantages\"). Note: At the Narrator’s discretion, heroes with Presence codes of “C” and lower may take this role with the understanding that, while such a hero may hope to use his sorcerous powers to achieve prosperity, he has yet to develop the business acumen needed to succeed. Such a hero may not have a starting wealth score higher than 3. Advantages Successful spell brokers are consum- mate showmen. Whether chatting privately in a small pub or on stage addressing a crowd of potential cus- tomers, these heroes know how to work an audience. They know the right questions to ask, the \n[PDF_PAGE 68 | score=3] action score is useless if the player allo- cated too few sorcery points, and many points must be spent and wasted if the action score is not high enough. Duration Score The chart below will help the Narrator determine the exact length of a success- ful long-term duration spell. Although this chart provides some exact figures, interpretation is encouraged. The only hard-and-fast rules should be that a duration score of 1 results in a mini mum length of one day, and no spell is ever truly permanent unless it has а duration score of at least 100. Other than this, Narrators are free to assign durations according to the needs of their campaigns. Duration Score Length of Spell 1 1 day 5 1 week 10\n[PDF_PAGE 17 | score=2] EA А) рм; ы ^ 2 ^y 2 Q N ~ e Disadvantages At first glance, having a role which encompasses the skills of both a war- rior and a sorcerer might seem slightly incongruous. Still, there is plenty of precedence for such an occupation, such as the Thorn Knights. However, becoming competent in two fields is sure to leave gaps in a heros knowledge and skills. While most sorcerers spend much battle mages become objects of ridicule and scorn. They never gain a trump bonus when attempting Presence actions with other sorcerers, except other battle mages or sorcerers currently attached to a military unit. (This drawback does not apply to Presence actions used to resist mystic magic.) Narrators are free"
  },
  "mechanics": {
    "topic": "attribute_bonuses",
    "keywords": [
      "add_2e",
      "attribute_bonuses",
      "bonus",
      "penalty",
      "tsr_inc_ad_and_d_2nd_edition_dragonlance_heroes_of_sorcery_text"
    ],
    "injection_priority": "support",
    "confidence": 1.0,
    "page_refs": [
      16,
      17,
      25,
      30,
      33,
      63,
      64,
      68
    ],
    "raw_text": "[PDF_PAGE 64 | score=12] Innovative Spells Spouting sorcerous theory and postu- lating about the required energy and potential effects of a new spell are one thing; actually casting it and achieving the desired results is quite another. No matter how well a sorcerer understands his art, things never translate exactly as expected when taking a spell from the- ory to practice. For this reason, the first success with a spell is more difficult to achieve than any other. Once a hero has actually produced the effect, repeating it is significantly easier. One thing that makes attempting new spells easier is abundant prepara- tion. A hero who reads a sorcerer's notes (or better yet, talks to him per- sonally) about similar \n[PDF_PAGE 63 | score=7] 2 Q DN ds z с: 254 Sis AS A ~ ¢ ay > S^ ^. NN Mi IX 1 ASA ) „кл CNN $ never increase and, іп most situations, the total difficulty will equal the base difficulty. However, the Narrator may assess a penalty to the base difficulty whenever he deems that the circum- stances surrounding the sorcerer make it hard for him to concentrate properly or might otherwise interfere with his spellcasting. Penalties should be assessed based on how disruptive the distraction is. A raucous noise or sudden jostle might be cause for a 1-point penalty, while casting a spell in the midst of a great battle may result in a 5-point penalty. Trying to keep enough concentration to cast while under the close scrutiny o\n[PDF_PAGE 30 | score=5] | must have Endurance scores of no the Order is particular about exactly how and by whom it is represented. The Knights expect nothing short of perfection from themselves, and they are equally demanding of their auxil- iary members. Requirements While the Knights themselves admit only civilized human and half-elf warriors into their ranks, the auxiliary is open to anyone who meets the rigid chivalric standards for entrance. Sorcerer heroes are more likely to encounter aloofness among the Knights because of their profession than from any kind of racism, for the Knights are not entirely comfortable with sorcery yet. Auxiliary members need not meet all the physical requirements demanded of Knig\n[PDF_PAGE 16 | score=3] battle, the Advantages While some might say that sorcerous skill alone is a huge advantage in a re one or two other points at which battle mages excel. Because sorcerers generally have had more education than the average sol- dier, they have had more exposure to Krynn's history, including military his- tory. This gives battle mages, who have also specialized in military exercises, a solid grip on military theory. While this does not help much in the middle of a skirmish, it does give these heroes an edge when making battle plans (though it does not necessarily make them qualified generals). When orga- nizing an attack or defense involving twenty-five or more people, a battle mage gains a +3 \n[PDF_PAGE 25 | score=3] ISON = — N ~ «S E \"di <А Advantages Once again, because being a Thorn Knight is a subsequent step from being a Knight of the Lily, these heroes maintain the martial advan- tages all Knights of Takhisis have. Any card played to close with the enemy during battle is automatically trump. Any card played for melee attack while the Knight is riding a mount is automatically trump. The hatred the Dark Knights feel for members of the Legion of Steel, how- ever, manifests itself differently in Thorn Knights. They do not get bonuses for melee combat as do Lily Knights. Instead, any cards played for sorcerous actions against Legionnaires are automatically trump. Furthermore, because of the emphasis the\n[PDF_PAGE 33 | score=3] мч Qib t VEN е, = SSS EE С у Y: the card used for the hero’s nature will come into play regularly (see “Disad- vantages\"). Note: At the Narrator’s discretion, heroes with Presence codes of “C” and lower may take this role with the understanding that, while such a hero may hope to use his sorcerous powers to achieve prosperity, he has yet to develop the business acumen needed to succeed. Such a hero may not have a starting wealth score higher than 3. Advantages Successful spell brokers are consum- mate showmen. Whether chatting privately in a small pub or on stage addressing a crowd of potential cus- tomers, these heroes know how to work an audience. They know the right questions to ask, the \n[PDF_PAGE 68 | score=3] action score is useless if the player allo- cated too few sorcery points, and many points must be spent and wasted if the action score is not high enough. Duration Score The chart below will help the Narrator determine the exact length of a success- ful long-term duration spell. Although this chart provides some exact figures, interpretation is encouraged. The only hard-and-fast rules should be that a duration score of 1 results in a mini mum length of one day, and no spell is ever truly permanent unless it has а duration score of at least 100. Other than this, Narrators are free to assign durations according to the needs of their campaigns. Duration Score Length of Spell 1 1 day 5 1 week 10\n[PDF_PAGE 17 | score=2] EA А) рм; ы ^ 2 ^y 2 Q N ~ e Disadvantages At first glance, having a role which encompasses the skills of both a war- rior and a sorcerer might seem slightly incongruous. Still, there is plenty of precedence for such an occupation, such as the Thorn Knights. However, becoming competent in two fields is sure to leave gaps in a heros knowledge and skills. While most sorcerers spend much battle mages become objects of ridicule and scorn. They never gain a trump bonus when attempting Presence actions with other sorcerers, except other battle mages or sorcerers currently attached to a military unit. (This drawback does not apply to Presence actions used to resist mystic magic.) Narrators are free"
  }
}
